edcompanion/__init__.py
edcompanion/_modidx.py
edcompanion/core.py
edcompanion/eddb/__init__.py
edcompanion/eddb/navigation.py
edcompanion/linalg/__init__.py
edcompanion/linalg/fitsvd.py
edcompanion/md/__init__.py
edcompanion/md/edastro.py
edcompanion-0.1.1.dist-info/LICENSE
edcompanion-0.1.1.dist-info/METADATA
edcompanion-0.1.1.dist-info/WHEEL
edcompanion-0.1.1.dist-info/entry_points.txt
edcompanion-0.1.1.dist-info/top_level.txt
edcompanion-0.1.1.dist-info/RECORD
