Metadata-Version: 2.1
Name: edcompanion
Version: 0.1.1
Summary: Faithful companion while out in the black. o7
Home-page: https://github.com/fenke/EDTravelCompanion
Author: Fenke Meijer
Author-email: 30428807+fenke@users.noreply.github.com
License: Apache Software License 2.0
Keywords: nbdev jupyter notebook python
Classifier: Development Status :: 4 - Beta
Classifier: Intended Audience :: Developers
Classifier: Natural Language :: English
Classifier: Programming Language :: Python :: 3.7
Classifier: Programming Language :: Python :: 3.8
Classifier: Programming Language :: Python :: 3.9
Classifier: Programming Language :: Python :: 3.10
Classifier: Programming Language :: Python :: 3.11
Classifier: Programming Language :: Python :: 3.12
Classifier: License :: OSI Approved :: Apache Software License
Requires-Python: >=3.7
License-File: LICENSE
Requires-Dist: fastcore
Requires-Dist: pandas
Requires-Dist: numpy
Requires-Dist: scikit-learn
Requires-Dist: matplotlib
Requires-Dist: seaborn
Requires-Dist: plotly
Provides-Extra: dev
Requires-Dist: fastcore; extra == "dev"
Requires-Dist: nbdev; extra == "dev"
Requires-Dist: jupyter; extra == "dev"
Requires-Dist: jupyterlab; extra == "dev"
Requires-Dist: pandas; extra == "dev"
Requires-Dist: numpy; extra == "dev"
Requires-Dist: scikit-learn; extra == "dev"
Requires-Dist: matplotlib; extra == "dev"
Requires-Dist: seaborn; extra == "dev"
Requires-Dist: plotly; extra == "dev"
